[
        {
            "id": 1,
            "title": "全球气候峰会呼吁采取紧急行动",
            "description": "各国领导人齐聚全球气候峰会，探讨应对气候变化的紧急策略，重点聚焦减少碳排放及推动可再生能源解决方案。",
            "image": "news-1.png"
        },
        {
            "id": 2,
            "title": "人工智能技术取得突破性进展",
            "description": "研究人员宣布人工智能领域取得重大突破性进展，这些新成果有望为医疗、金融等多个行业带来革命性变革。",
            "image": "news-2.png"
        },
        {
            "id": 3,
            "title": "全新太空任务计划探索遥远星系",
            "description": "美国国家航空航天局（NASA）公布了一项全新太空任务计划，该任务将致力于探索遥远星系，以期揭示宇宙起源的相关奥秘。",
            "image": "news-3.png"
        },
        {
            "id": 4,
            "title": "全球经济复苏背景下股市创历史新高",
            "description": "随着全球疫情带来的挑战逐步缓解，经济复苏迹象持续显现，全球股市已攀升至历史新高水平。",
            "image": "news-4.png"
        }
]